LICENSE
README.md
setup.py
basic_toolkit/__init__.py
basic_toolkit/type.py
basic_toolkit.egg-info/PKG-INFO
basic_toolkit.egg-info/SOURCES.txt
basic_toolkit.egg-info/dependency_links.txt
basic_toolkit.egg-info/top_level.txt
basic_toolkit/math/__init__.py
basic_toolkit/math/hermite.py
basic_toolkit/math/matrix4.py