Metadata-Version: 2.1
Name: basic-toolkit
Version: 0.4.3
Summary: python3常用的工具类方法汇总
Home-page: https://github.com/hai2007/tool.py
Author: hai2007
Author-email: 2501482523@qq.com
License: MIT
Classifier: Programming Language :: Python :: 3
Classifier: License :: OSI Approved :: MIT License
Classifier: Operating System :: OS Independent
License-File: LICENSE
